asterisk_mcp_server/__init__.py
asterisk_mcp_server/cli.py
asterisk_mcp_server/server.py
asterisk_mcp_server/ui/__init__.py
asterisk_mcp_server/ui/settings.py
asterisk_mcp_server-0.1.1.dist-info/METADATA
asterisk_mcp_server-0.1.1.dist-info/WHEEL
asterisk_mcp_server-0.1.1.dist-info/entry_points.txt
asterisk_mcp_server-0.1.1.dist-info/licenses/LICENSE
asterisk_mcp_server-0.1.1.dist-info/RECORD
