Metadata-Version: 2.4
Name: asterisk-mcp-server
Version: 0.1.1
Summary: A Model Context Protocol (MCP) server that provides security scanning capabilities for code snippets, codebases, and verification of code changes
Project-URL: Homepage, https://mcp.asterisk.so
Project-URL: Bug Tracker, https://github.com/getasterisk/asterisk-mcp-server/issues
Project-URL: Documentation, https://github.com/getAsterisk/asterisk-mcp-server/blob/main/README.md
Author-email: Asterisk <hello@asterisk.so>
License:                                  Apache License
License-File: LICENSE
Classifier: Development Status :: 4 - Beta
Classifier: Intended Audience :: Developers
Classifier: License :: OSI Approved :: Apache Software License
Classifier: Programming Language :: Python :: 3
Classifier: Programming Language :: Python :: 3.10
Classifier: Programming Language :: Python :: 3.11
Classifier: Programming Language :: Python :: 3.12
Classifier: Topic :: Security
Classifier: Topic :: Software Development :: Libraries :: Python Modules
Requires-Python: >=3.10
Requires-Dist: dearpygui
Requires-Dist: httpx
Requires-Dist: mcp[cli]
Provides-Extra: cli
Requires-Dist: mcp[cli]; extra == 'cli'
Provides-Extra: dev
Requires-Dist: black; extra == 'dev'
Requires-Dist: build; extra == 'dev'
Requires-Dist: isort; extra == 'dev'
Requires-Dist: mypy; extra == 'dev'
Requires-Dist: pytest; extra == 'dev'
Requires-Dist: twine; extra == 'dev'
